pytask_stata/__init__.py
pytask_stata/_version.py
pytask_stata/cli.py
pytask_stata/collect.py
pytask_stata/config.py
pytask_stata/execute.py
pytask_stata/plugin.py
pytask_stata/py.typed
pytask_stata/shared.py
pytask_stata-0.5.0.dist-info/METADATA
pytask_stata-0.5.0.dist-info/WHEEL
pytask_stata-0.5.0.dist-info/entry_points.txt
pytask_stata-0.5.0.dist-info/licenses/LICENSE
pytask_stata-0.5.0.dist-info/RECORD
