Metadata-Version: 2.4
Name: pytask_stata
Version: 0.5.0
Summary: Execute do-files with Stata and pytask.
Project-URL: Homepage, https://github.com/pytask-dev/pytask-stata
Project-URL: Documentation, https://github.com/pytask-dev/pytask-stata
Project-URL: Github, https://github.com/pytask-dev/pytask-stata
Project-URL: Tracker, https://github.com/pytask-dev/pytask-stata/issues
Project-URL: Changelog, https://github.com/pytask-dev/pytask-stata/blob/main/CHANGES.md
Author-email: Tobias Raabe <raabe@posteo.de>
License: MIT
License-File: LICENSE
Classifier: Development Status :: 4 - Beta
Classifier: License :: OSI Approved :: MIT License
Classifier: Operating System :: OS Independent
Classifier: Programming Language :: Python :: 3
Classifier: Programming Language :: Python :: 3 :: Only
Requires-Python: >=3.9
Requires-Dist: click!=8.2.0,>=8.1.8
Requires-Dist: pytask>=0.5.2
